sim/input_handler.v
module input_handler(
    clk,
    rst,
    byte_available,
    byte,
    command,
    data_count,
    buffer,
    ready,
);

input clk;
input rst;
input byte_available;
input [7:0]byte;


output reg [3:0] command;
output reg [15:0] data_count;
output reg [BUFFER_SIZE:0] buffer;
output reg ready;



//STATES
parameter BUFFER_SIZE			 = 255;
parameter STATE_IDLE             = 8'h0;
parameter STATE_READ_ID  		 = 8'h1;
parameter STATE_READ_CONTROL     = 8'h2;
parameter STATE_READ_DATA_SIZE   = 8'h3;
parameter STATE_READ_DATA        = 8'h4;

parameter CHAR_L = 16'h4C;

parameter CHAR_0 = 16'h30;

//Registers
reg [7:0]  r_STATE    = 'b0;

reg r_low_byte          = 0;
reg [15:0] r_count      = 0;

reg r_prev_byte_available = 0;


//Wire
wire pos_edge_byte_available;

//Assign
assign pos_edge_byte_available = (byte_available & ~r_prev_byte_available);

//Synchronous
always @ (posedge clk) begin
    r_prev_byte_available <= byte_available;
end

always @ (posedge clk) begin

    if (rst) begin
        command     <= 'h0;
        data_count  <= 16'h00;
        buffer      <= 0;
        r_STATE     <= STATE_IDLE;
        r_low_byte  <= 0;
		ready		<= 0;

    end
    else begin
        //main state machine goes here
        case (r_STATE)
            STATE_IDLE: begin
                command         <= 8'h0;
                data_count      <= 16'h00;
				ready			<= 0;
                if (pos_edge_byte_available) begin
                    r_STATE     <= STATE_READ_ID;
                end
            end
            STATE_READ_ID: begin
                data_count      <= 16'h00;
                r_low_byte      <= 0;
                if (byte == CHAR_L) begin
                    //read the first of byte
                    r_STATE     <= STATE_READ_CONTROL;
                end
                else begin
                    r_STATE 	<= STATE_IDLE;
                end
			end
            STATE_READ_CONTROL: begin
                
                if (pos_edge_byte_available) begin
                    if ((byte < CHAR_0) || (byte > CHAR_0 + 15)) begin
                        r_STATE    <=    STATE_READ_ID;
                    end
                    else begin
                        r_STATE    <=    STATE_READ_DATA_SIZE;
                        command    <=    (byte - CHAR_0);
                    end
                end
            end
            STATE_READ_DATA_SIZE: begin
                //read the size
                if (pos_edge_byte_available) begin
                    if ((byte < CHAR_0) || (byte > CHAR_0 + 15)) begin
                        r_STATE    <=    STATE_READ_ID;
                    end
                    else begin
                        if (!r_low_byte) begin
                            //low_byte
                            data_count[7:0]    <= (byte - CHAR_0);
                            r_low_byte 			<= 1;
                        end
                        else begin
                            //high byte
                            data_count    <=  (data_count[7:0] << 4) + (byte - CHAR_0);
                            r_count       <=  (data_count[7:0] << 4)+ (byte - CHAR_0); 
                            r_STATE <= STATE_READ_DATA;
                        end
                    end                
                end
            end
            STATE_READ_DATA : begin
                if (pos_edge_byte_available) begin
                    if ((byte < CHAR_0) || (byte > CHAR_0 + 15)) begin
                        r_STATE    <=    STATE_READ_ID;
                    end
                    else begin
                        //reading data
//NEED TO READ DATA INTO THE BUFFER                          
						buffer <= {buffer[251 : 0], byte[3:0]};
						if (r_count == 1) begin
							//reached the end of the data
							r_STATE <= STATE_IDLE;
							ready <= 1;
						end

						r_count <= (r_count - 1);
                    end
                end
            end
            default: begin
                command         <= 8'h0;
                r_STATE         <= STATE_IDLE;
            end
        endcase
        
    end
end
endmodule

sim/input_handler_tb.v
module input_handler_tb;
	//make a reset that pulses once
	reg rst = 0;
	reg clk = 0;

	//input handler specific registers
	reg 			byte_available 	= 0;
	reg  [7:0] 		byte			= 0;
	wire [3:0]		command;
	wire [15:0] 	data_count;
	wire [255:0] 	buffer;
	wire 			ready;

	input_handler ih (
		.clk(clk),
		.rst(rst),
		.byte_available(byte_available),
		.byte(byte),
		.command(command),
		.data_count(data_count),
		.buffer(buffer),
		.ready(ready));

	initial begin
		$dumpfile("design.vcd");
		$dumpvars(0, input_handler_tb);
		$dumpvars(0, ih);

		#	1 		rst = 1;
		#	5 		rst = 0;
		#	10		
//SEND ID as ASCII 'L'
					byte = 16'h4C;
					byte_available = 1;
		#	14		
					byte_available = 0;

//Send command '1' as ASCII '1'
		#	20
					byte = 16'h31;
					byte_available = 1;
		#	14
					byte_available = 0;
//Send data size 0x12 as ASCII '1', '0'
		#	30		
					byte = 16'h31;
					byte_available = 1;
		#	34		
					byte_available = 0;
		#	40	
					byte = 16'h30;
					byte_available = 1;
		#	44		
					byte_available = 0;
//Send data 0x0123456789ABCDEF
		#	50	
					byte = 16'h30;
					byte_available = 1;
		#	54		
					byte_available = 0;
		#	60	
					byte = 16'h31;
					byte_available = 1;
		#	64		
					byte_available = 0;
		#	70	
					byte = 16'h32;
					byte_available = 1;
		#	74		
					byte_available = 0;
		#	80	
					byte = 16'h33;
					byte_available = 1;
		#	84		
					byte_available = 0;
		#	90	
					byte = 16'h34;
					byte_available = 1;
		#	94		
					byte_available = 0;
		#	100	
					byte = 16'h35;
					byte_available = 1;
		#	104		
					byte_available = 0;
		#	110	
					byte = 16'h36;
					byte_available = 1;
		#	114		
					byte_available = 0;
		#	120	
					byte = 16'h37;
					byte_available = 1;
		#	124		
					byte_available = 0;
		#	130	
					byte = 16'h38;
					byte_available = 1;
		#	134		
					byte_available = 0;
		#	140	
					byte = 16'h39;
					byte_available = 1;
		#	144		
					byte_available = 0;
		#	150	
					byte = 16'h3A;
					byte_available = 1;
		#	154		
					byte_available = 0;
		#	160	
					byte = 16'h3B;
					byte_available = 1;
		#	164		
					byte_available = 0;
		#	170	
					byte = 16'h3C;
					byte_available = 1;
		#	174		
					byte_available = 0;
		#	180	
					byte = 16'h3D;
					byte_available = 1;
		#	184		
					byte_available = 0;
		#	190	
					byte = 16'h3E;
					byte_available = 1;
		#	194		
					byte_available = 0;
		#	200	
					byte = 16'h3F;
					byte_available = 1;
		#	214		
					byte_available = 0;
		

//finished
		#	220		
					byte = 16'h30;
					byte_available = 1;
		#	224
					byte_available = 0;

		# 	230  	$finish;

	end

	always #4 clk = ~clk;

	initial $monitor ("%t: byte = %h, count = %d, ready = %h, buffer = %h", $time, byte, data_count, ready, buffer);
endmodule

sim/design.vcd
$date
	Sat Apr 16 14:42:31 2011
$end
$version
	Icarus Verilog
$end
$timescale
	1s
$end
$scope module input_handler_tb $end
$var wire 256 ! buffer [255:0] $end
$var wire 4 " command [3:0] $end
$var wire 16 # data_count [15:0] $end
$var wire 1 $ ready $end
$var reg 8 % byte [7:0] $end
$var reg 1 & byte_available $end
$var reg 1 ' clk $end
$var reg 1 ( rst $end
$scope module ih $end
$var wire 8 ) byte [7:0] $end
$var wire 1 * byte_available $end
$var wire 1 + clk $end
$var wire 1 , pos_edge_byte_available $end
$var wire 1 - rst $end
$var reg 256 . buffer [255:0] $end
$var reg 4 / command [3:0] $end
$var reg 16 0 data_count [15:0] $end
$var reg 8 1 r_STATE [7:0] $end
$var reg 16 2 r_count [15:0] $end
$var reg 1 3 r_low_byte $end
$var reg 1 4 r_prev_byte_available $end
$var reg 1 5 ready $end
$upscope $end
$upscope $end
$scope module input_handler_tb $end
$scope module ih $end
$upscope $end
$upscope $end
$enddefinitions $end
#0
$dumpvars
x5
04
03
b0 2
b0 1
bx 0
bx /
bx .
0-
0,
0+
0*
b0 )
0(
0'
0&
b0 %
x$
bx #
bx "
bx !
$end
#1
1(
1-
#4
05
0$
b0 .
b0 !
b0 0
b0 #
b0 /
b0 "
1'
1+
#6
0(
0-
#8
0'
0+
#12
1'
1+
#16
1,
0'
0+
1&
1*
b1001100 %
b1001100 )
#20
0,
14
b1 1
1'
1+
#24
0'
0+
#28
b10 1
1'
1+
#30
0&
0*
#32
0'
0+
#36
04
1'
1+
#40
0'
0+
#44
1'
1+
#48
0'
0+
#50
1,
1&
1*
b110001 %
b110001 )
#52
0,
14
b1 /
b1 "
b11 1
1'
1+
#56
0'
0+
#60
1'
1+
#64
0'
0+
0&
0*
#68
04
1'
1+
#72
0'
0+
#76
1'
1+
#80
0'
0+
#84
1'
1+
#88
0'
0+
#92
1'
1+
#94
1,
1&
1*
#96
0'
0+
#100
0,
14
13
b1 0
b1 #
1'
1+
#104
0'
0+
#108
1'
1+
#112
0'
0+
#116
1'
1+
#120
0'
0+
#124
1'
1+
#128
0'
0+
0&
0*
#132
04
1'
1+
#136
0'
0+
#140
1'
1+
#144
0'
0+
#148
1'
1+
#152
0'
0+
#156
1'
1+
#160
0'
0+
#164
1'
1+
#168
1,
0'
0+
1&
1*
b110000 %
b110000 )
#172
0,
b100 1
b10000 2
b10000 0
b10000 #
14
1'
1+
#176
0'
0+
#180
1'
1+
#184
0'
0+
#188
1'
1+
#192
0'
0+
#196
1'
1+
#200
0'
0+
#204
1'
1+
#208
0'
0+
#212
04
1'
1+
0&
0*
#216
0'
0+
#220
1'
1+
#224
0'
0+
#228
1'
1+
#232
0'
0+
#236
1'
1+
#240
0'
0+
#244
1'
1+
#248
0'
0+
#252
1'
1+
#256
0'
0+
#260
1'
1+
#262
1,
1&
1*
#264
0'
0+
#268
0,
b1111 2
14
1'
1+
#272
0'
0+
#276
1'
1+
#280
0'
0+
#284
1'
1+
#288
0'
0+
#292
1'
1+
#296
0'
0+
#300
1'
1+
#304
0'
0+
#308
1'
1+
#312
0'
0+
#316
04
1'
1+
0&
0*
#320
0'
0+
#324
1'
1+
#328
0'
0+
#332
1'
1+
#336
0'
0+
#340
1'
1+
#344
0'
0+
#348
1'
1+
#352
0'
0+
#356
1'
1+
#360
0'
0+
#364
1'
1+
#368
0'
0+
#372
1'
1+
#376
1,
0'
0+
1&
1*
b110001 %
b110001 )
#380
0,
b1110 2
b1 .
b1 !
14
1'
1+
#384
0'
0+
#388
1'
1+
#392
0'
0+
#396
1'
1+
#400
0'
0+
#404
1'
1+
#408
0'
0+
#412
1'
1+
#416
0'
0+
#420
1'
1+
#424
0'
0+
#428
1'
1+
#432
0'
0+
#436
1'
1+
#440
0'
0+
0&
0*
#444
04
1'
1+
#448
0'
0+
#452
1'
1+
#456
0'
0+
#460
1'
1+
#464
0'
0+
#468
1'
1+
#472
0'
0+
#476
1'
1+
#480
0'
0+
#484
1'
1+
#488
0'
0+
#492
1'
1+
#496
0'
0+
#500
1'
1+
#504
0'
0+
#508
1'
1+
#510
1,
1&
1*
b110010 %
b110010 )
#512
0'
0+
#516
0,
14
b1101 2
b10010 .
b10010 !
1'
1+
#520
0'
0+
#524
1'
1+
#528
0'
0+
#532
1'
1+
#536
0'
0+
#540
1'
1+
#544
0'
0+
#548
1'
1+
#552
0'
0+
#556
1'
1+
#560
0'
0+
#564
1'
1+
#568
0'
0+
#572
1'
1+
#576
0'
0+
#580
1'
1+
#584
0'
0+
0&
0*
#588
04
1'
1+
#592
0'
0+
#596
1'
1+
#600
0'
0+
#604
1'
1+
#608
0'
0+
#612
1'
1+
#616
0'
0+
#620
1'
1+
#624
0'
0+
#628
1'
1+
#632
0'
0+
#636
1'
1+
#640
0'
0+
#644
1'
1+
#648
0'
0+
#652
1'
1+
#656
0'
0+
#660
1'
1+
#664
1,
0'
0+
1&
1*
b110011 %
b110011 )
#668
0,
b1100 2
b100100011 .
b100100011 !
14
1'
1+
#672
0'
0+
#676
1'
1+
#680
0'
0+
#684
1'
1+
#688
0'
0+
#692
1'
1+
#696
0'
0+
#700
1'
1+
#704
0'
0+
#708
1'
1+
#712
0'
0+
#716
1'
1+
#720
0'
0+
#724
1'
1+
#728
0'
0+
#732
1'
1+
#736
0'
0+
#740
1'
1+
#744
0'
0+
#748
04
1'
1+
0&
0*
#752
0'
0+
#756
1'
1+
#760
0'
0+
#764
1'
1+
#768
0'
0+
#772
1'
1+
#776
0'
0+
#780
1'
1+
#784
0'
0+
#788
1'
1+
#792
0'
0+
#796
1'
1+
#800
0'
0+
#804
1'
1+
#808
0'
0+
#812
1'
1+
#816
0'
0+
#820
1'
1+
#824
0'
0+
#828
1'
1+
#832
0'
0+
#836
1'
1+
#838
1,
1&
1*
b110100 %
b110100 )
#840
0'
0+
#844
0,
b1011 2
b1001000110100 .
b1001000110100 !
14
1'
1+
#848
0'
0+
#852
1'
1+
#856
0'
0+
#860
1'
1+
#864
0'
0+
#868
1'
1+
#872
0'
0+
#876
1'
1+
#880
0'
0+
#884
1'
1+
#888
0'
0+
#892
1'
1+
#896
0'
0+
#900
1'
1+
#904
0'
0+
#908
1'
1+
#912
0'
0+
#916
1'
1+
#920
0'
0+
#924
1'
1+
#928
0'
0+
#932
04
1'
1+
0&
0*
#936
0'
0+
#940
1'
1+
#944
0'
0+
#948
1'
1+
#952
0'
0+
#956
1'
1+
#960
0'
0+
#964
1'
1+
#968
0'
0+
#972
1'
1+
#976
0'
0+
#980
1'
1+
#984
0'
0+
#988
1'
1+
#992
0'
0+
#996
1'
1+
#1000
0'
0+
#1004
1'
1+
#1008
0'
0+
#1012
1'
1+
#1016
0'
0+
#1020
1'
1+
#1024
0'
0+
#1028
1'
1+
#1032
1,
0'
0+
1&
1*
b110101 %
b110101 )
#1036
0,
b1010 2
b10010001101000101 .
b10010001101000101 !
14
1'
1+
#1040
0'
0+
#1044
1'
1+
#1048
0'
0+
#1052
1'
1+
#1056
0'
0+
#1060
1'
1+
#1064
0'
0+
#1068
1'
1+
#1072
0'
0+
#1076
1'
1+
#1080
0'
0+
#1084
1'
1+
#1088
0'
0+
#1092
1'
1+
#1096
0'
0+
#1100
1'
1+
#1104
0'
0+
#1108
1'
1+
#1112
0'
0+
#1116
1'
1+
#1120
0'
0+
#1124
1'
1+
#1128
0'
0+
#1132
1'
1+
#1136
0'
0+
0&
0*
#1140
04
1'
1+
#1144
0'
0+
#1148
1'
1+
#1152
0'
0+
#1156
1'
1+
#1160
0'
0+
#1164
1'
1+
#1168
0'
0+
#1172
1'
1+
#1176
0'
0+
#1180
1'
1+
#1184
0'
0+
#1188
1'
1+
#1192
0'
0+
#1196
1'
1+
#1200
0'
0+
#1204
1'
1+
#1208
0'
0+
#1212
1'
1+
#1216
0'
0+
#1220
1'
1+
#1224
0'
0+
#1228
1'
1+
#1232
0'
0+
#1236
1'
1+
#1240
0'
0+
#1244
1'
1+
#1246
1,
1&
1*
b110110 %
b110110 )
#1248
0'
0+
#1252
0,
14
b1001 2
b100100011010001010110 .
b100100011010001010110 !
1'
1+
#1256
0'
0+
#1260
1'
1+
#1264
0'
0+
#1268
1'
1+
#1272
0'
0+
#1276
1'
1+
#1280
0'
0+
#1284
1'
1+
#1288
0'
0+
#1292
1'
1+
#1296
0'
0+
#1300
1'
1+
#1304
0'
0+
#1308
1'
1+
#1312
0'
0+
#1316
1'
1+
#1320
0'
0+
#1324
1'
1+
#1328
0'
0+
#1332
1'
1+
#1336
0'
0+
#1340
1'
1+
#1344
0'
0+
#1348
1'
1+
#1352
0'
0+
#1356
1'
1+
#1360
0'
0+
0&
0*
#1364
04
1'
1+
#1368
0'
0+
#1372
1'
1+
#1376
0'
0+
#1380
1'
1+
#1384
0'
0+
#1388
1'
1+
#1392
0'
0+
#1396
1'
1+
#1400
0'
0+
#1404
1'
1+
#1408
0'
0+
#1412
1'
1+
#1416
0'
0+
#1420
1'
1+
#1424
0'
0+
#1428
1'
1+
#1432
0'
0+
#1436
1'
1+
#1440
0'
0+
#1444
1'
1+
#1448
0'
0+
#1452
1'
1+
#1456
0'
0+
#1460
1'
1+
#1464
0'
0+
#1468
1'
1+
#1472
0'
0+
#1476
1'
1+
#1480
1,
0'
0+
1&
1*
b110111 %
b110111 )
#1484
0,
b1000 2
b1001000110100010101100111 .
b1001000110100010101100111 !
14
1'
1+
#1488
0'
0+
#1492
1'
1+
#1496
0'
0+
#1500
1'
1+
#1504
0'
0+
#1508
1'
1+
#1512
0'
0+
#1516
1'
1+
#1520
0'
0+
#1524
1'
1+
#1528
0'
0+
#1532
1'
1+
#1536
0'
0+
#1540
1'
1+
#1544
0'
0+
#1548
1'
1+
#1552
0'
0+
#1556
1'
1+
#1560
0'
0+
#1564
1'
1+
#1568
0'
0+
#1572
1'
1+
#1576
0'
0+
#1580
1'
1+
#1584
0'
0+
#1588
1'
1+
#1592
0'
0+
#1596
1'
1+
#1600
0'
0+
#1604
04
1'
1+
0&
0*
#1608
0'
0+
#1612
1'
1+
#1616
0'
0+
#1620
1'
1+
#1624
0'
0+
#1628
1'
1+
#1632
0'
0+
#1636
1'
1+
#1640
0'
0+
#1644
1'
1+
#1648
0'
0+
#1652
1'
1+
#1656
0'
0+
#1660
1'
1+
#1664
0'
0+
#1668
1'
1+
#1672
0'
0+
#1676
1'
1+
#1680
0'
0+
#1684
1'
1+
#1688
0'
0+
#1692
1'
1+
#1696
0'
0+
#1700
1'
1+
#1704
0'
0+
#1708
1'
1+
#1712
0'
0+
#1716
1'
1+
#1720
0'
0+
#1724
1'
1+
#1728
0'
0+
#1732
1'
1+
#1734
1,
1&
1*
b111000 %
b111000 )
#1736
0'
0+
#1740
0,
b111 2
b10010001101000101011001111000 .
b10010001101000101011001111000 !
14
1'
1+
#1744
0'
0+
#1748
1'
1+
#1752
0'
0+
#1756
1'
1+
#1760
0'
0+
#1764
1'
1+
#1768
0'
0+
#1772
1'
1+
#1776
0'
0+
#1780
1'
1+
#1784
0'
0+
#1788
1'
1+
#1792
0'
0+
#1796
1'
1+
#1800
0'
0+
#1804
1'
1+
#1808
0'
0+
#1812
1'
1+
#1816
0'
0+
#1820
1'
1+
#1824
0'
0+
#1828
1'
1+
#1832
0'
0+
#1836
1'
1+
#1840
0'
0+
#1844
1'
1+
#1848
0'
0+
#1852
1'
1+
#1856
0'
0+
#1860
1'
1+
#1864
0'
0+
#1868
04
1'
1+
0&
0*
#1872
0'
0+
#1876
1'
1+
#1880
0'
0+
#1884
1'
1+
#1888
0'
0+
#1892
1'
1+
#1896
0'
0+
#1900
1'
1+
#1904
0'
0+
#1908
1'
1+
#1912
0'
0+
#1916
1'
1+
#1920
0'
0+
#1924
1'
1+
#1928
0'
0+
#1932
1'
1+
#1936
0'
0+
#1940
1'
1+
#1944
0'
0+
#1948
1'
1+
#1952
0'
0+
#1956
1'
1+
#1960
0'
0+
#1964
1'
1+
#1968
0'
0+
#1972
1'
1+
#1976
0'
0+
#1980
1'
1+
#1984
0'
0+
#1988
1'
1+
#1992
0'
0+
#1996
1'
1+
#2000
0'
0+
#2004
1'
1+
#2008
1,
0'
0+
1&
1*
b111001 %
b111001 )
#2012
0,
b110 2
b100100011010001010110011110001001 .
b100100011010001010110011110001001 !
14
1'
1+
#2016
0'
0+
#2020
1'
1+
#2024
0'
0+
#2028
1'
1+
#2032
0'
0+
#2036
1'
1+
#2040
0'
0+
#2044
1'
1+
#2048
0'
0+
#2052
1'
1+
#2056
0'
0+
#2060
1'
1+
#2064
0'
0+
#2068
1'
1+
#2072
0'
0+
#2076
1'
1+
#2080
0'
0+
#2084
1'
1+
#2088
0'
0+
#2092
1'
1+
#2096
0'
0+
#2100
1'
1+
#2104
0'
0+
#2108
1'
1+
#2112
0'
0+
#2116
1'
1+
#2120
0'
0+
#2124
1'
1+
#2128
0'
0+
#2132
1'
1+
#2136
0'
0+
#2140
1'
1+
#2144
0'
0+
#2148
1'
1+
#2152
0'
0+
0&
0*
#2156
04
1'
1+
#2160
0'
0+
#2164
1'
1+
#2168
0'
0+
#2172
1'
1+
#2176
0'
0+
#2180
1'
1+
#2184
0'
0+
#2188
1'
1+
#2192
0'
0+
#2196
1'
1+
#2200
0'
0+
#2204
1'
1+
#2208
0'
0+
#2212
1'
1+
#2216
0'
0+
#2220
1'
1+
#2224
0'
0+
#2228
1'
1+
#2232
0'
0+
#2236
1'
1+
#2240
0'
0+
#2244
1'
1+
#2248
0'
0+
#2252
1'
1+
#2256
0'
0+
#2260
1'
1+
#2264
0'
0+
#2268
1'
1+
#2272
0'
0+
#2276
1'
1+
#2280
0'
0+
#2284
1'
1+
#2288
0'
0+
#2292
1'
1+
#2296
0'
0+
#2300
1'
1+
#2302
1,
1&
1*
b111010 %
b111010 )
#2304
0'
0+
#2308
0,
14
b101 2
b1001000110100010101100111100010011010 .
b1001000110100010101100111100010011010 !
1'
1+
#2312
0'
0+
#2316
1'
1+
#2320
0'
0+
#2324
1'
1+
#2328
0'
0+
#2332
1'
1+
#2336
0'
0+
#2340
1'
1+
#2344
0'
0+
#2348
1'
1+
#2352
0'
0+
#2356
1'
1+
#2360
0'
0+
#2364
1'
1+
#2368
0'
0+
#2372
1'
1+
#2376
0'
0+
#2380
1'
1+
#2384
0'
0+
#2388
1'
1+
#2392
0'
0+
#2396
1'
1+
#2400
0'
0+
#2404
1'
1+
#2408
0'
0+
#2412
1'
1+
#2416
0'
0+
#2420
1'
1+
#2424
0'
0+
#2428
1'
1+
#2432
0'
0+
#2436
1'
1+
#2440
0'
0+
#2444
1'
1+
#2448
0'
0+
#2452
1'
1+
#2456
0'
0+
0&
0*
#2460
04
1'
1+
#2464
0'
0+
#2468
1'
1+
#2472
0'
0+
#2476
1'
1+
#2480
0'
0+
#2484
1'
1+
#2488
0'
0+
#2492
1'
1+
#2496
0'
0+
#2500
1'
1+
#2504
0'
0+
#2508
1'
1+
#2512
0'
0+
#2516
1'
1+
#2520
0'
0+
#2524
1'
1+
#2528
0'
0+
#2532
1'
1+
#2536
0'
0+
#2540
1'
1+
#2544
0'
0+
#2548
1'
1+
#2552
0'
0+
#2556
1'
1+
#2560
0'
0+
#2564
1'
1+
#2568
0'
0+
#2572
1'
1+
#2576
0'
0+
#2580
1'
1+
#2584
0'
0+
#2588
1'
1+
#2592
0'
0+
#2596
1'
1+
#2600
0'
0+
#2604
1'
1+
#2608
0'
0+
#2612
1'
1+
#2616
1,
0'
0+
1&
1*
b111011 %
b111011 )
#2620
0,
b100 2
b10010001101000101011001111000100110101011 .
b10010001101000101011001111000100110101011 !
14
1'
1+
#2624
0'
0+
#2628
1'
1+
#2632
0'
0+
#2636
1'
1+
#2640
0'
0+
#2644
1'
1+
#2648
0'
0+
#2652
1'
1+
#2656
0'
0+
#2660
1'
1+
#2664
0'
0+
#2668
1'
1+
#2672
0'
0+
#2676
1'
1+
#2680
0'
0+
#2684
1'
1+
#2688
0'
0+
#2692
1'
1+
#2696
0'
0+
#2700
1'
1+
#2704
0'
0+
#2708
1'
1+
#2712
0'
0+
#2716
1'
1+
#2720
0'
0+
#2724
1'
1+
#2728
0'
0+
#2732
1'
1+
#2736
0'
0+
#2740
1'
1+
#2744
0'
0+
#2748
1'
1+
#2752
0'
0+
#2756
1'
1+
#2760
0'
0+
#2764
1'
1+
#2768
0'
0+
#2772
1'
1+
#2776
0'
0+
#2780
04
1'
1+
0&
0*
